ExtraDecorators/__init__.py
ExtraDecorators/private.py
ExtraDecorators/read_only.py
ExtraDecorators/restoreAttributeTypeIntegrity.py
ExtraDecorators/validatetyping.py
extradecorators-0.4.dist-info/LICENCE
extradecorators-0.4.dist-info/METADATA
extradecorators-0.4.dist-info/WHEEL
extradecorators-0.4.dist-info/top_level.txt
extradecorators-0.4.dist-info/RECORD
